dpypeline/__init__.py
dpypeline/akita/__init__.py
dpypeline/akita/core.py
dpypeline/akita/directory_state.py
dpypeline/akita/event_handler.py
dpypeline/akita/factory.py
dpypeline/akita/queue_events.py
dpypeline/cli/__init__.py
dpypeline/cli/argument_parser.py
dpypeline/cli/main_cli.py
dpypeline/cli/yaml_constructors.py
dpypeline/cli/yaml_executers.py
dpypeline/cli/yaml_loader.py
dpypeline/etl_pipeline/__init__.py
dpypeline/etl_pipeline/basic_pipeline.py
dpypeline/etl_pipeline/core.py
dpypeline/etl_pipeline/decorators.py
dpypeline/etl_pipeline/thread_pipeline.py
dpypeline/event_consumer/__init__.py
dpypeline/event_consumer/consumer_parallel.py
dpypeline/event_consumer/consumer_serial.py
dpypeline/event_consumer/core.py
dpypeline/filesystems/__init__.py
dpypeline/filesystems/object_store.py
dpypeline-0.1.0b4.dist-info/LICENCE.md
dpypeline-0.1.0b4.dist-info/METADATA
dpypeline-0.1.0b4.dist-info/WHEEL
dpypeline-0.1.0b4.dist-info/entry_points.txt
dpypeline-0.1.0b4.dist-info/top_level.txt
dpypeline-0.1.0b4.dist-info/RECORD
