Metadata-Version: 2.1
Name: dpypeline
Version: 0.1.0b4
Summary: Program for creating data pipelines triggered by file creation events.
Author: Joao Morado
Author-email: joao.morado@noc.ac.uk
Maintainer-email: Joao Morado <joao.morado@noc.ac.uk>
Project-URL: repository, https://github.com/NOC-OI/data-pypeline
Keywords: data,pipeline,data-pypeline,dpypeline,pypeline,noc
Classifier: Programming Language :: Python :: 3
Classifier: Intended Audience :: Science/Research
Requires-Python: >=3.9
License-File: LICENCE.md
Requires-Dist: dask >=2023.3.0
Requires-Dist: dask-jobqueue >=0.8.1
Requires-Dist: s3fs >=2023.3.0
Requires-Dist: celery ==5.2.7
Requires-Dist: fsspec >=2023.3.0
Requires-Dist: watchdog ==2.3.1
Provides-Extra: test
Requires-Dist: pytest >=7.2.0 ; extra == 'test'
